OlympusTrader/__init__.py
OlympusTrader/alpha/__init__.py
OlympusTrader/alpha/base_alpha.py
OlympusTrader/alpha/ema_price_crossover.py
OlympusTrader/alpha/rsi_divergance_alpha.py
OlympusTrader/alpha/test_entry.py
OlympusTrader/broker/TradingViewBroker.py
OlympusTrader/broker/__init__.py
OlympusTrader/broker/alpaca_broker.py
OlympusTrader/broker/base_broker.py
OlympusTrader/broker/ccxt_broker.py
OlympusTrader/broker/interfaces.py
OlympusTrader/broker/mt5_broker.py
OlympusTrader/broker/paper_broker.py
OlympusTrader/broker/templateBroker.py
OlympusTrader/broker/tradingTwoOneTwo_broker.py
OlympusTrader/insight/__init__.py
OlympusTrader/insight/executors/README.md
OlympusTrader/insight/executors/__init__.py
OlympusTrader/insight/executors/base_executor.py
OlympusTrader/insight/executors/canceled/__init__.py
OlympusTrader/insight/executors/canceled/defaultOnCancelled.py
OlympusTrader/insight/executors/closed/__init__.py
OlympusTrader/insight/executors/closed/defaultOnClosed.py
OlympusTrader/insight/executors/executed/__init__.py
OlympusTrader/insight/executors/filled/__init__.py
OlympusTrader/insight/executors/filled/basicStopLoss.py
OlympusTrader/insight/executors/filled/basicTakeProfit.py
OlympusTrader/insight/executors/filled/closeExhaustedInsight.py
OlympusTrader/insight/executors/filled/closeMarketChanged.py
OlympusTrader/insight/executors/general/__init__.py
OlympusTrader/insight/executors/general/allExecutor.py
OlympusTrader/insight/executors/general/anyExecutor.py
OlympusTrader/insight/executors/new/__init__.py
OlympusTrader/insight/executors/new/allowTradingWindow.py
OlympusTrader/insight/executors/new/cancelAllOppositeSide.py
OlympusTrader/insight/executors/new/dynamicQuantityToRisk.py
OlympusTrader/insight/executors/new/fullAccountQuantiityToRisk.py
OlympusTrader/insight/executors/new/marketOrderEntryPrice.py
OlympusTrader/insight/executors/new/minimumRiskToReward.py
OlympusTrader/insight/executors/new/percentageDCALevels.py
olympustrader-0.3.5.5.dist-info/METADATA
olympustrader-0.3.5.5.dist-info/WHEEL
olympustrader-0.3.5.5.dist-info/RECORD
