Metadata-Version: 2.3
Name: olympustrader
Version: 0.3.5.5
Summary: trading bot framework
License: Apache 2.0
Keywords: Trading bot,Framework,backtesting,trading,HFT
Author: Moustapha Diaby
Author-email: me@isaacdiaby.tech
Requires-Python: ==3.12.*
Classifier: Development Status :: 3 - Alpha
Classifier: Intended Audience :: Developers
Classifier: Intended Audience :: Financial and Insurance Industry
Classifier: License :: Other/Proprietary License
Classifier: Operating System :: MacOS
Classifier: Operating System :: Microsoft :: Windows
Classifier: Operating System :: POSIX
Classifier: Operating System :: Unix
Classifier: Programming Language :: Python
Classifier: Programming Language :: Python :: 3
Classifier: Programming Language :: Python :: 3.12
Classifier: Programming Language :: Python :: 3 :: Only
Classifier: Topic :: Office/Business :: Financial
Classifier: Topic :: Office/Business :: Financial :: Investment
Classifier: Topic :: Software Development :: Libraries :: Application Frameworks
Classifier: Typing :: Typed
Provides-Extra: metatrader
Provides-Extra: talib
Requires-Dist: MetaTrader5 (>=5.0,<6.0) ; extra == "metatrader"
Requires-Dist: alpaca-py (>=0.34.0,<0.35.0)
Requires-Dist: ccxt (>=4.4.38,<5.0.0)
Requires-Dist: dash (>=2.18.2,<3.0.0)
Requires-Dist: dash-tvlwc (>=0.1.1,<0.2.0)
Requires-Dist: nest-asyncio (>=1.6.0,<2.0.0)
Requires-Dist: numpy (>=1.20,<2.0)
Requires-Dist: pandas (>=2.2.3,<3.0.0)
Requires-Dist: pandas-ta (>=0.3.14b,<0.4.0)
Requires-Dist: python-dotenv (>=1.0.1,<2.0.0)
Requires-Dist: quantstats (>=0.0.62,<0.0.63)
Requires-Dist: scipy (>=1.14.0,<2.0.0)
Requires-Dist: setuptools (>=72.1.0,<73.0.0)
Requires-Dist: ta-lib (>=0.5.1,<0.6.0) ; extra == "talib"
Requires-Dist: tables (>=3.10,<4.0)
Requires-Dist: tqdm (>=4.67.1,<5.0.0)
Requires-Dist: vectorbt (==0.27.2)
Requires-Dist: yfinance (>=0.2.50,<0.3.0)
Project-URL: Documentation, https://olympustrader.readthedocs.io/en/latest/
Project-URL: Homepage, https://olympustrader.readthedocs.io/en/latest/
Project-URL: Repository, https://github.com/isaac-diaby/OlympusTrader
